Keycloak/KeycloakClientApi.py
Keycloak/__init__.py
MitreidConnect/MitreidClientApi.py
MitreidConnect/__init__.py
ServiceRegistryAms/PullPublish.py
ServiceRegistryAms/__init__.py
Utils/__init__.py
Utils/common.py
Utils/oauth.py
rciam_federation_registry_agent-3.3.3.data/scripts/deployer_keycloak
rciam_federation_registry_agent-3.3.3.data/scripts/deployer_mitreid
rciam_federation_registry_agent-3.3.3.data/scripts/deployer_ssp
tests/__init__.py
tests/test_deployer_keycloak.py
tests/test_deployer_mitreid.py
tests/test_deployer_ssp.py
rciam_federation_registry_agent-3.3.3.dist-info/LICENSE
rciam_federation_registry_agent-3.3.3.dist-info/METADATA
rciam_federation_registry_agent-3.3.3.dist-info/WHEEL
rciam_federation_registry_agent-3.3.3.dist-info/top_level.txt
rciam_federation_registry_agent-3.3.3.dist-info/RECORD
