Metadata-Version: 2.1
Name: rciam-federation-registry-agent
Version: 3.3.3
Summary: A library that connects to ams using argo-ams-library and syncs with MITREid, SimpleSAMLphp and Keycloak
Home-page: https://github.com/rciam/rciam-federation-registry-agent
Author: grnet
Author-email: faai@grnet.gr
License: ASL 2.0
Classifier: License :: OSI Approved :: Apache Software License
Classifier: Programming Language :: PHP
Classifier: Programming Language :: Python
Classifier: Programming Language :: Python :: 3.5
Classifier: Programming Language :: Python :: 3.6
Classifier: Programming Language :: Python :: 3.7
License-File: LICENSE
Requires-Dist: argo-ams-library >=0.5.9
Requires-Dist: certifi ==2023.5.7
Requires-Dist: chardet ==4.0.0
Requires-Dist: idna ==3.3
Requires-Dist: oauthlib ==3.2.2
Requires-Dist: requests-oauthlib ==1.3.1
Requires-Dist: requests ==2.27.1
Requires-Dist: types-requests ==2.30.0.0
Requires-Dist: urllib3 ==1.26.9
